maesyorikun/__init__.py
maesyorikun/maesyorikun.py
maesyorikun/test.py
maesyorikun-0.1.5.dist-info/METADATA
maesyorikun-0.1.5.dist-info/WHEEL
maesyorikun-0.1.5.dist-info/top_level.txt
maesyorikun-0.1.5.dist-info/RECORD
